django_lastdayofmonth/__init__.py
django_lastdayofmonth/apps.py
django_lastdayofmonth/functions.py
django_lastdayofmonth-1.2.1.dist-info/licenses/LICENSE
django_lastdayofmonth-1.2.1.dist-info/METADATA
django_lastdayofmonth-1.2.1.dist-info/WHEEL
django_lastdayofmonth-1.2.1.dist-info/top_level.txt
django_lastdayofmonth-1.2.1.dist-info/RECORD
