Metadata-Version: 2.4
Name: django-lastdayofmonth
Version: 1.2.1
Summary: Cross-database LastDayOfMonth function for Django ORM
Author-email: Beniamino Nobile <beniaminonobile@gmail.com>
License: MIT
Project-URL: Homepage, https://github.com/nobilebeniamino/django-lastdayofmonth
Keywords: django,orm,last day,date functions,calendar,postgresql,sqlite
Classifier: Framework :: Django :: 3.2
Classifier: Framework :: Django :: 4.2
Classifier: Framework :: Django :: 5.2
Classifier: Programming Language :: Python :: 3
Classifier: Programming Language :: Python :: 3.8
Classifier: Programming Language :: Python :: 3.9
Classifier: Programming Language :: Python :: 3.10
Classifier: Programming Language :: Python :: 3.11
Classifier: Programming Language :: Python :: 3.12
Classifier: Programming Language :: Python :: 3.13
Classifier: License :: OSI Approved :: MIT License
Requires-Python: >=3.8
License-File: LICENSE
Requires-Dist: Django<=6.0,>=3.2
Provides-Extra: dev
Requires-Dist: dj-database-url<0.6; extra == "dev"
Requires-Dist: pytest; extra == "dev"
Requires-Dist: pytest-django; extra == "dev"
Requires-Dist: tox; extra == "dev"
Dynamic: license-file
